filesweep/__init__.py
filesweep/cleaner.py
filesweep/scanner.py
filesweep-0.1.1.dist-info/licenses/LICENSE
filesweep-0.1.1.dist-info/METADATA
filesweep-0.1.1.dist-info/WHEEL
filesweep-0.1.1.dist-info/entry_points.txt
filesweep-0.1.1.dist-info/top_level.txt
filesweep-0.1.1.dist-info/RECORD
