Metadata-Version: 2.4
Name: filesweep
Version: 0.1.1
Summary: A tool for managing and organizing files in a directory
Home-page: https://github.com/rakshithkalmadi/FileSweep
Author: Rakshith Kalmadi
Author-email: Rakshith Kalmadi <rakshithkalmadi@gmail.com>
License-Expression: MIT
Project-URL: Bug Reports, https://github.com/rakshithkalmadi/FileSweep/issues
Project-URL: Source, https://github.com/rakshithkalmadi/FileSweep
Keywords: file management,file organization,cleanup,file scanner
Classifier: Programming Language :: Python :: 3
Classifier: Programming Language :: Python :: 3.6
Classifier: Programming Language :: Python :: 3.7
Classifier: Programming Language :: Python :: 3.8
Classifier: Programming Language :: Python :: 3.9
Classifier: Operating System :: OS Independent
Classifier: Topic :: Utilities
Requires-Python: >=3.6
License-File: LICENSE
Dynamic: author
Dynamic: home-page
Dynamic: license-file
Dynamic: requires-python
